{
  "projects": [
    {
      "date": "06/07/2023",
      "title": "Indian Gold",
      "description": "The platform supports market orders, limit orders, and stop-loss orders, service charges, giving users flexibility in executing trades.",
      "url": " https://indiansgold.com",
      "imgSrc": "https://cdn.pixabay.com/photo/2018/06/07/16/49/virtual-3460451_960_720.jpg"
    },

    {
      "date": "11/10/2023",
      "title": "Vivaacp",
      "description": "Entire site is dynamic like cms, crafting fully customizable and dynamic websites using Laravel, seo-friendly architecture and optimization in multiple languages.",
      "url": "https://react-video-app-eight.vercel.app",
      "imgSrc": "https://cdn.pixabay.com/photo/2016/11/21/12/51/mobile-phone-1845233__340.jpg"
    },
    {
      "date": "01/08/2022",
      "title": "TVS Insurance",
      "description": "Insurance platform designed to streamline policy management, claims processing, and customer interactions, Integrated secure payment gateways and many more.",
      "url": "https://www.mybizznow.com/tvs/",
      "imgSrc": "https://cdn.pixabay.com/photo/2019/12/14/08/36/shopping-4694470_960_720.jpg"
    },
    {
      "date": "01/01/2022",
      "title": "MLM",
      "description": "Architected and developed a comprehensive MLM level plan platform, encompassing features such as multi-tiered commission structures, genealogy tracking, and performance analytics.",
      "url": "https://reactcryptocoin.vercel.app/",
      "imgSrc": "https://cdn.pixabay.com/photo/2017/12/12/12/44/bitcoin-3014614_960_720.jpg"
    },
    {
      "date": "15/10/2023",
      "title": "XCrypto",
      "description": "The Cryptocoin basic app with real-time market data and comprehensive graphs spanning from 7 days to 1 year. This is personal project based on React Js.",
      "url": "https://reactcryptocoin.vercel.app/",
      "imgSrc": "https://cdn.pixabay.com/photo/2017/12/12/12/44/bitcoin-3014614_960_720.jpg"
    },
    {
      "date": "20/06/2024",
      "title": "PORTFOLIO",
      "description": "A portfolio is a compilation of academic and professional materials that exemplifies your beliefs, skills, qualifications, education, training, and experiences.",
      "url": "/",
      "imgSrc": "https://cdn.pixabay.com/photo/2020/03/19/21/25/cactus-4948833_960_720.jpg"
    }
  ]

}
